{
  "tests": [
    {
      "name": "01 - Ticket Pricing",
      "setup": "npm ci",
      "run": "NODE_OPTIONS=--experimental-vm-modules npx jest tests/01-ticket-pricing.spec.js --verbose",
      "timeout": 30,
      "points": 8
    },
    {
      "name": "02 - Traffic Light",
      "setup": "",
      "run": "NODE_OPTIONS=--experimental-vm-modules npx jest tests/02-traffic-light.spec.js --verbose",
      "timeout": 30,
      "points": 8
    },
    {
      "name": "03 - Grade Calculator",
      "setup": "",
      "run": "NODE_OPTIONS=--experimental-vm-modules npx jest tests/03-grade-calculator.spec.js --verbose",
      "timeout": 30,
      "points": 8
    },
    {
      "name": "04 - Weather Advice",
      "setup": "",
      "run": "NODE_OPTIONS=--experimental-vm-modules npx jest tests/04-weather-advice.spec.js --verbose",
      "timeout": 30,
      "points": 8
    },
    {
      "name": "05 - Library Card",
      "setup": "",
      "run": "NODE_OPTIONS=--experimental-vm-modules npx jest tests/05-library-card.spec.js --verbose",
      "timeout": 30,
      "points": 8
    },
    {
      "name": "06 - Shipping Calculator",
      "setup": "",
      "run": "NODE_OPTIONS=--experimental-vm-modules npx jest tests/06-shipping-calculator.spec.js --verbose",
      "timeout": 30,
      "points": 9
    },
    {
      "name": "07 - Coffee Shop",
      "setup": "",
      "run": "NODE_OPTIONS=--experimental-vm-modules npx jest tests/07-coffee-shop.spec.js --verbose",
      "timeout": 30,
      "points": 9
    },
    {
      "name": "08 - Tax Calculator",
      "setup": "",
      "run": "NODE_OPTIONS=--experimental-vm-modules npx jest tests/08-tax-calculator.spec.js --verbose",
      "timeout": 30,
      "points": 9
    },
    {
      "name": "09 - Password Strength",
      "setup": "",
      "run": "NODE_OPTIONS=--experimental-vm-modules npx jest tests/09-password-strength.spec.js --verbose",
      "timeout": 30,
      "points": 9
    },
    {
      "name": "10 - Tip Calculator",
      "setup": "",
      "run": "NODE_OPTIONS=--experimental-vm-modules npx jest tests/10-tip-calculator.spec.js --verbose",
      "timeout": 30,
      "points": 8
    },
    {
      "name": "11 - Parking Fee",
      "setup": "",
      "run": "NODE_OPTIONS=--experimental-vm-modules npx jest tests/11-parking-fee.spec.js --verbose",
      "timeout": 30,
      "points": 8
    },
    {
      "name": "12 - Season Activity",
      "setup": "",
      "run": "NODE_OPTIONS=--experimental-vm-modules npx jest tests/12-season-activity.spec.js --verbose",
      "timeout": 30,
      "points": 8
    }
  ]
}
